{
  "_class": "shapePath",
  "booleanOperation": -1,
  "clippingMaskMode": 0,
  "do_objectID": "A98AA35E-789A-45DC-8EC0-BAABADC199B1",
  "edited": true,
  "exportOptions": {
    "_class": "exportOptions",
    "exportFormats": [
    ],
    "includedLayerIds": [
    ],
    "layerOptions": 0,
    "shouldTrim": false
  },
  "frame": {
    "_class": "rect",
    "constrainProportions": false,
    "height": 21.55399999999997,
    "width": 15.77500000000003,
    "x": 248.1175,
    "y": 226.8492
  },
  "hasClippingMask": false,
  "isClosed": true,
  "isFixedToViewport": false,
  "isFlippedHorizontal": false,
  "isFlippedVertical": false,
  "isLocked": false,
  "isVisible": true,
  "layerListExpandedType": 0,
  "name": "Fill 70",
  "nameIsFixed": false,
  "pointRadiusBehaviour": 1,
  "points": [
    {
      "_class": "curvePoint",
      "cornerRadius": 0,
      "curveFrom": "{0.2715689381933446, 0.81548668460610652}",
      "curveMode": 4,
      "curveTo": "{0.22846275752773412, 0.71610837895518331}",
      "hasCurveFrom": true,
      "hasCurveTo": false,
      "point": "{0.22846275752773412, 0.71610837895518331}"
    },
    {
      "_class": "curvePoint",
      "cornerRadius": 0,
      "curveFrom": "{0.68316957210776319, 0.86123225387399138}",
      "curveMode": 3,
      "curveTo": "{0.38364500792393075, 0.86123225387399138}",
      "hasCurveFrom": true,
      "hasCurveTo": true,
      "point": "{0.52805071315372565, 0.86123225387399138}"
    },
    {
      "_class": "curvePoint",
      "cornerRadius": 0,
      "curveFrom": "{0.78446909667194764, 0.64985617518790117}",
      "curveMode": 3,
      "curveTo": "{0.78446909667194764, 0.80759951749095316}",
      "hasCurveFrom": true,
      "hasCurveTo": true,
      "point": "{0.78446909667194764, 0.71768581237821349}"
    },
    {
      "_class": "curvePoint",
      "cornerRadius": 0,
      "curveFrom": "{0.59264659270998221, 0.58675883826667941}",
      "curveMode": 4,
      "curveTo": "{0.73058637083993716, 0.61042033961213693}",
      "hasCurveFrom": false,
      "hasCurveTo": true,
      "point": "{0.59264659270998221, 0.58675883826667941}"
    },
    {
      "_class": "curvePoint",
      "cornerRadius": 0,
      "curveFrom": "{0.18535657686212362, 0.515820729330983}",
      "curveMode": 4,
      "curveTo": "{0.36849445324881169, 0.54732300269091771}",
      "hasCurveFrom": true,
      "hasCurveTo": false,
      "point": "{0.36849445324881169, 0.54732300269091771}"
    },
    {
      "_class": "curvePoint",
      "cornerRadius": 0,
      "curveFrom": "{0.038795562599050516, 0.12303980699638072}",
      "curveMode": 2,
      "curveTo": "{0.038795562599050516, 0.44321239677090141}",
      "hasCurveFrom": true,
      "hasCurveTo": true,
      "point": "{0.038795562599050516, 0.28709288299155589}"
    },
    {
      "_class": "curvePoint",
      "cornerRadius": 0,
      "curveFrom": "{0.7758478605388277, 0}",
      "curveMode": 3,
      "curveTo": "{0.22199683042789237, 0}",
      "hasCurveFrom": true,
      "hasCurveTo": true,
      "point": "{0.48919175911251955, 0}"
    },
    {
      "_class": "curvePoint",
      "cornerRadius": 0,
      "curveFrom": "{0.99137876386687651, 0.26816368191519147}",
      "curveMode": 4,
      "curveTo": "{0.94396196513470598, 0.10726547276607658}",
      "hasCurveFrom": false,
      "hasCurveTo": true,
      "point": "{0.99137876386687651, 0.26816368191519147}"
    },
    {
      "_class": "curvePoint",
      "cornerRadius": 0,
      "curveFrom": "{0.73274167987321714, 0.1956017444557861}",
      "curveMode": 4,
      "curveTo": "{0.76722662440570411, 0.26816368191519147}",
      "hasCurveFrom": true,
      "hasCurveTo": false,
      "point": "{0.76722662440570411, 0.26816368191519147}"
    },
    {
      "_class": "curvePoint",
      "cornerRadius": 0,
      "curveFrom": "{0.34916006339144201, 0.1388141412266875}",
      "curveMode": 3,
      "curveTo": "{0.64868462757527623, 0.1388141412266875}",
      "hasCurveFrom": true,
      "hasCurveTo": true,
      "point": "{0.49134706814579954, 0.1388141412266875}"
    },
    {
      "_class": "curvePoint",
      "cornerRadius": 0,
      "curveFrom": "{0.25217115689381936, 0.33757075252853391}",
      "curveMode": 3,
      "curveTo": "{0.25217115689381936, 0.19244687760972579}",
      "hasCurveFrom": true,
      "hasCurveTo": true,
      "point": "{0.25217115689381936, 0.2728959821842819}"
    },
    {
      "_class": "curvePoint",
      "cornerRadius": 0,
      "curveFrom": "{0.42668779714738564, 0.39909065602672295}",
      "curveMode": 4,
      "curveTo": "{0.30820919175911332, 0.37858402152732834}",
      "hasCurveFrom": false,
      "hasCurveTo": true,
      "point": "{0.42668779714738564, 0.39909065602672295}"
    },
    {
      "_class": "curvePoint",
      "cornerRadius": 0,
      "curveFrom": "{0.86421553090332859, 0.47323002690915844}",
      "curveMode": 4,
      "curveTo": "{0.65730586370839972, 0.43852649160248725}",
      "hasCurveFrom": true,
      "hasCurveTo": false,
      "point": "{0.65730586370839972, 0.43852649160248725}"
    },
    {
      "_class": "curvePoint",
      "cornerRadius": 0,
      "curveFrom": "{1, 0.888002226964833}",
      "curveMode": 3,
      "curveTo": "{1, 0.5615199034981917}",
      "hasCurveFrom": true,
      "hasCurveTo": true,
      "point": "{1, 0.70664377841699977}"
    },
    {
      "_class": "curvePoint",
      "cornerRadius": 0,
      "curveFrom": "{0.24786053882725936, 1}",
      "curveMode": 2,
      "curveTo": "{0.80171156893819107, 1}",
      "hasCurveFrom": true,
      "hasCurveTo": true,
      "point": "{0.52805071315372565, 1}"
    },
    {
      "_class": "curvePoint",
      "cornerRadius": 0,
      "curveFrom": "{0, 0.71610837895518331}",
      "curveMode": 4,
      "curveTo": "{0.047416798732172249, 0.89588939407998636}",
      "hasCurveFrom": false,
      "hasCurveTo": true,
      "point": "{0, 0.71610837895518331}"
    }
  ],
  "resizingConstraint": 63,
  "resizingType": 0,
  "rotation": 0,
  "shouldBreakMaskChain": false,
  "style": {
    "_class": "style",
    "endMarkerType": 0,
    "fills": [
      {
        "_class": "fill",
        "color": {
          "_class": "color",
          "alpha": 1,
          "blue": 0,
          "green": 0.7647058823529411,
          "red": 1
        },
        "fillType": 0,
        "isEnabled": true,
        "noiseIndex": 0,
        "noiseIntensity": 0,
        "patternFillType": 1,
        "patternTileScale": 1
      }
    ],
    "miterLimit": 10,
    "startMarkerType": 0,
    "windingRule": 1
  }
}