{
  "_class": "shapeGroup",
  "booleanOperation": 0,
  "clippingMaskMode": 0,
  "do_objectID": "70F822B7-9A37-40F5-874A-003B943AD665",
  "exportOptions": {
    "_class": "exportOptions",
    "do_objectID": "43D9B81B-044B-4EFC-B507-2D6F7C6EC5DF",
    "exportFormats": [
    ],
    "includedLayerIds": [
    ],
    "layerOptions": 0,
    "shouldTrim": false
  },
  "frame": {
    "_class": "rect",
    "constrainProportions": false,
    "do_objectID": "BBD53900-21A4-48F3-8D5E-3759657D3D9C",
    "height": 6.294736842105262,
    "width": 19.43753227851074,
    "x": 0.5876104576139151,
    "y": 0.1754317434209042
  },
  "hasClickThrough": false,
  "hasClippingMask": false,
  "isFixedToViewport": false,
  "isFlippedHorizontal": false,
  "isFlippedVertical": false,
  "isLocked": false,
  "isVisible": true,
  "layerListExpandedType": 0,
  "layers": [
    {
      "class": "shapePath",
      "id": "A5B24E6C-765E-4679-B8BC-13E31D73805C"
    },
    {
      "class": "shapePath",
      "id": "535B51E8-F073-4DDC-852A-46356E4FD9D8"
    },
    {
      "class": "shapePath",
      "id": "BEAA4911-F320-4304-92AD-DCD562BFF5FE"
    }
  ],
  "name": "Path 10",
  "nameIsFixed": false,
  "resizingConstraint": 63,
  "resizingType": 0,
  "rotation": 0,
  "shouldBreakMaskChain": false,
  "style": {
    "_class": "style",
    "blur": {
      "_class": "blur",
      "center": "{0.5, 0.5}",
      "do_objectID": "D0B94968-2F44-4656-9889-FCA560F914C3",
      "isEnabled": false,
      "motionAngle": 0,
      "radius": 5.999999642372131,
      "saturation": 1,
      "type": 0
    },
    "borders": [
      {
        "_class": "border",
        "color": {
          "_class": "color",
          "alpha": 1,
          "blue": 1,
          "green": 1,
          "red": 1
        },
        "fillType": 0,
        "isEnabled": false,
        "position": 0,
        "thickness": 1.499999910593033
      }
    ],
    "do_objectID": "FD29F1D1-C589-4FFC-BD65-82724EDE821D",
    "endMarkerType": 0,
    "fills": [
      {
        "_class": "fill",
        "color": {
          "_class": "color",
          "alpha": 1,
          "blue": 1,
          "green": 1,
          "red": 1
        },
        "fillType": 0,
        "isEnabled": true,
        "noiseIndex": 0,
        "noiseIntensity": 0,
        "patternFillType": 1,
        "patternTileScale": 1
      }
    ],
    "miterLimit": 10,
    "startMarkerType": 0,
    "windingRule": 1
  },
  "userInfo": {
    "com.animaapp.stc-sketch-plugin": {
      "kModelPropertiesKey": {
      }
    }
  },
  "windingRule": 1
}