{
  "_class": "shapePath",
  "booleanOperation": -1,
  "clippingMaskMode": 0,
  "do_objectID": "2F568680-CF0A-4F6B-AED7-0EF33B6DBE10",
  "edited": true,
  "exportOptions": {
    "_class": "exportOptions",
    "exportFormats": [
    ],
    "includedLayerIds": [
    ],
    "layerOptions": 0,
    "shouldTrim": false
  },
  "frame": {
    "_class": "rect",
    "constrainProportions": false,
    "height": 7.848388609715267,
    "width": 6.386086956521723,
    "x": 94.43478260869563,
    "y": 4.041439195979923
  },
  "hasClippingMask": false,
  "isClosed": true,
  "isFixedToViewport": false,
  "isFlippedHorizontal": false,
  "isFlippedVertical": false,
  "isLocked": false,
  "isVisible": true,
  "layerListExpandedType": 1,
  "name": "Shape",
  "nameIsFixed": false,
  "pointRadiusBehaviour": 1,
  "points": [
    {
      "_class": "curvePoint",
      "cornerRadius": 0,
      "curveFrom": "{0.99991830065359866, 1.0000000000000004}",
      "curveMode": 1,
      "curveTo": "{0.99991830065359866, 1.0000000000000004}",
      "hasCurveFrom": false,
      "hasCurveTo": false,
      "point": "{0.99991830065359866, 1.0000000000000004}"
    },
    {
      "_class": "curvePoint",
      "cornerRadius": 0,
      "curveFrom": "{0, 1.0000000000000004}",
      "curveMode": 1,
      "curveTo": "{0, 1.0000000000000004}",
      "hasCurveFrom": false,
      "hasCurveTo": false,
      "point": "{0, 1.0000000000000004}"
    },
    {
      "_class": "curvePoint",
      "cornerRadius": 0,
      "curveFrom": "{0, 0.85809870818151734}",
      "curveMode": 1,
      "curveTo": "{0, 0.85809870818151734}",
      "hasCurveFrom": false,
      "hasCurveTo": false,
      "point": "{0, 0.85809870818151734}"
    },
    {
      "_class": "curvePoint",
      "cornerRadius": 0,
      "curveFrom": "{0.63325163398692985, 0.18694932096720832}",
      "curveMode": 1,
      "curveTo": "{0.63325163398692985, 0.18694932096720832}",
      "hasCurveFrom": false,
      "hasCurveTo": false,
      "point": "{0.63325163398692985, 0.18694932096720832}"
    },
    {
      "_class": "curvePoint",
      "cornerRadius": 0,
      "curveFrom": "{0.027777777777775899, 0.18694932096720832}",
      "curveMode": 1,
      "curveTo": "{0.027777777777775899, 0.18694932096720832}",
      "hasCurveFrom": false,
      "hasCurveTo": false,
      "point": "{0.027777777777775899, 0.18694932096720832}"
    },
    {
      "_class": "curvePoint",
      "cornerRadius": 0,
      "curveFrom": "{0.027777777777775899, 0}",
      "curveMode": 1,
      "curveTo": "{0.027777777777775899, 0}",
      "hasCurveFrom": false,
      "hasCurveTo": false,
      "point": "{0.027777777777775899, 0}"
    },
    {
      "_class": "curvePoint",
      "cornerRadius": 0,
      "curveFrom": "{0.98880718954248559, 0}",
      "curveMode": 1,
      "curveTo": "{0.98880718954248559, 0}",
      "hasCurveFrom": false,
      "hasCurveTo": false,
      "point": "{0.98880718954248559, 0}"
    },
    {
      "_class": "curvePoint",
      "cornerRadius": 0,
      "curveFrom": "{0.98880718954248559, 0.14190129181848302}",
      "curveMode": 1,
      "curveTo": "{0.98880718954248559, 0.14190129181848302}",
      "hasCurveFrom": false,
      "hasCurveTo": false,
      "point": "{0.98880718954248559, 0.14190129181848302}"
    },
    {
      "_class": "curvePoint",
      "cornerRadius": 0,
      "curveFrom": "{0.35833333333333278, 0.81311692613448361}",
      "curveMode": 1,
      "curveTo": "{0.35833333333333278, 0.81311692613448361}",
      "hasCurveFrom": false,
      "hasCurveTo": false,
      "point": "{0.35833333333333278, 0.81311692613448361}"
    },
    {
      "_class": "curvePoint",
      "cornerRadius": 0,
      "curveFrom": "{1.000000000000002, 0.81311692613448361}",
      "curveMode": 1,
      "curveTo": "{1.000000000000002, 0.81311692613448361}",
      "hasCurveFrom": false,
      "hasCurveTo": false,
      "point": "{1.000000000000002, 0.81311692613448361}"
    }
  ],
  "resizingConstraint": 63,
  "resizingType": 0,
  "rotation": 0,
  "shouldBreakMaskChain": false,
  "style": {
    "_class": "style",
    "endMarkerType": 0,
    "fills": [
      {
        "_class": "fill",
        "color": {
          "_class": "color",
          "alpha": 1,
          "blue": 0.09803921568627451,
          "green": 0.09803921568627451,
          "red": 0.09803921568627451
        },
        "fillType": 0,
        "isEnabled": true,
        "noiseIndex": 0,
        "noiseIntensity": 0,
        "patternFillType": 1,
        "patternTileScale": 1
      }
    ],
    "miterLimit": 10,
    "startMarkerType": 0,
    "windingRule": 0
  }
}