{
  "_class": "group",
  "booleanOperation": 0,
  "clippingMaskMode": 0,
  "do_objectID": "387FFDA9-F215-4267-90C0-0893D60E26B9",
  "exportOptions": {
    "_class": "exportOptions",
    "exportFormats": [
    ],
    "includedLayerIds": [
    ],
    "layerOptions": 0,
    "shouldTrim": false
  },
  "frame": {
    "_class": "rect",
    "constrainProportions": false,
    "height": 568,
    "width": 570,
    "x": 0,
    "y": 2408
  },
  "hasClickThrough": false,
  "hasClippingMask": false,
  "isFixedToViewport": false,
  "isFlippedHorizontal": false,
  "isFlippedVertical": false,
  "isLocked": false,
  "isVisible": true,
  "layerListExpandedType": 2,
  "layers": [
    {
      "class": "group",
      "id": "D782BBAC-D6FA-4AE3-B91E-1D949CEDCE30"
    },
    {
      "class": "symbolInstance",
      "id": "470D3094-192B-4F71-B986-1F1EAF7BF587"
    }
  ],
  "name": "content-uitklapper copy 4",
  "nameIsFixed": true,
  "resizingConstraint": 58,
  "resizingType": 0,
  "rotation": 0,
  "shouldBreakMaskChain": false,
  "style": {
    "_class": "style",
    "endMarkerType": 0,
    "miterLimit": 10,
    "startMarkerType": 0,
    "windingRule": 1
  },
  "userInfo": {
    "com.animaapp.stc-sketch-plugin": {
      "kModelPropertiesKey": {
        "align": 0,
        "isCollapsing": 1,
        "spacing": 0,
        "type": 0
      },
      "kViewTypeKey": "ADModelStackView"
    }
  }
}