{
  "_class": "shapePath",
  "booleanOperation": -1,
  "clippingMaskMode": 0,
  "do_objectID": "5FD3EB7F-9735-4456-A8FD-0CF8797B754F",
  "edited": true,
  "exportOptions": {
    "_class": "exportOptions",
    "exportFormats": [
    ],
    "includedLayerIds": [
    ],
    "layerOptions": 0,
    "shouldTrim": false
  },
  "frame": {
    "_class": "rect",
    "constrainProportions": false,
    "height": 5.044552567090751,
    "width": 2.913652173913102,
    "x": 11.56069565217398,
    "y": 5.208725044133114
  },
  "hasClippingMask": false,
  "isClosed": true,
  "isFixedToViewport": false,
  "isFlippedHorizontal": false,
  "isFlippedVertical": false,
  "isLocked": false,
  "isVisible": true,
  "layerListExpandedType": 0,
  "name": "Path",
  "nameIsFixed": false,
  "pointRadiusBehaviour": 1,
  "points": [
    {
      "_class": "curvePoint",
      "cornerRadius": 0,
      "curveFrom": "{0.91616164266379674, 0.079892407816471597}",
      "curveMode": 4,
      "curveTo": "{0.99999999999999234, 0.20631492337756163}",
      "hasCurveFrom": true,
      "hasCurveTo": false,
      "point": "{0.99999999999999234, 0.20631492337756163}"
    },
    {
      "_class": "curvePoint",
      "cornerRadius": 0,
      "curveFrom": "{0.2101799623959146, 0}",
      "curveMode": 3,
      "curveTo": "{0.74679547096089938, 0.00017921663374861075}",
      "hasCurveFrom": true,
      "hasCurveTo": true,
      "point": "{0.56164383561643427, 0}"
    },
    {
      "_class": "curvePoint",
      "cornerRadius": 0,
      "curveFrom": "{0, 0.78669135040625449}",
      "curveMode": 2,
      "curveTo": "{0, 0.21330864959374837}",
      "hasCurveFrom": true,
      "hasCurveTo": true,
      "point": "{0, 0.50005142445747219}"
    },
    {
      "_class": "curvePoint",
      "cornerRadius": 0,
      "curveFrom": "{0.74679547096090704, 0.99982078336625435}",
      "curveMode": 3,
      "curveTo": "{0.21004566210045714, 1}",
      "hasCurveFrom": true,
      "hasCurveTo": true,
      "point": "{0.56164383561643427, 1}"
    },
    {
      "_class": "curvePoint",
      "cornerRadius": 0,
      "curveFrom": "{1, 0.79368507662244125}",
      "curveMode": 4,
      "curveTo": "{0.91616164266379674, 0.92010759218353133}",
      "hasCurveFrom": false,
      "hasCurveTo": true,
      "point": "{1, 0.79368507662244125}"
    }
  ],
  "resizingConstraint": 63,
  "resizingType": 0,
  "rotation": 0,
  "shouldBreakMaskChain": false,
  "style": {
    "_class": "style",
    "endMarkerType": 0,
    "fills": [
      {
        "_class": "fill",
        "color": {
          "_class": "color",
          "alpha": 1,
          "blue": 0.09803921568627451,
          "green": 0.09803921568627451,
          "red": 0.09803921568627451
        },
        "fillType": 0,
        "isEnabled": true,
        "noiseIndex": 0,
        "noiseIntensity": 0,
        "patternFillType": 1,
        "patternTileScale": 1
      }
    ],
    "miterLimit": 10,
    "startMarkerType": 0,
    "windingRule": 0
  }
}